feedback_transformer_pytorch/__init__.py
feedback_transformer_pytorch/feedback_transformer_pytorch.py
feedback_transformer_pytorch-0.0.11.dist-info/LICENSE
feedback_transformer_pytorch-0.0.11.dist-info/METADATA
feedback_transformer_pytorch-0.0.11.dist-info/WHEEL
feedback_transformer_pytorch-0.0.11.dist-info/top_level.txt
feedback_transformer_pytorch-0.0.11.dist-info/RECORD
