Metadata-Version: 2.1
Name: feedback-transformer-pytorch
Version: 0.0.11
Summary: Implementation of Feedback Transformer in Pytorch
Home-page: https://github.com/lucidrains/feedback-transformer-pytorch
Author: Phil Wang
Author-email: lucidrains@gmail.com
License: MIT
Keywords: attention,artificial intelligence,transformer,deep learning,memory
Platform: UNKNOWN
Classifier: Development Status :: 4 - Beta
Classifier: Intended Audience :: Developers
Classifier: Topic :: Scientific/Engineering :: Artificial Intelligence
Classifier: License :: OSI Approved :: MIT License
Classifier: Programming Language :: Python :: 3.6
Requires-Dist: torch (>=1.6)
Requires-Dist: einops
